aiida_cp2k/__init__.py
aiida_cp2k/calculations.py
aiida_cp2k/parsers.py
aiida_cp2k/utils.py
aiida_cp2k/workflows.py
aiida_cp2k/tests/__init__.py
aiida_cp2k/tests/test_bands.py
aiida_cp2k/tests/test_dft.py
aiida_cp2k/tests/test_failure.py
aiida_cp2k/tests/test_geopt.py
aiida_cp2k/tests/test_input_generator.py
aiida_cp2k/tests/test_mm.py
aiida_cp2k/tests/test_parser.py
aiida_cp2k/tests/test_precision.py
aiida_cp2k/tests/test_restart.py
aiida_cp2k_ng-1.0.0b2.data/data/setup.json
aiida_cp2k_ng-1.0.0b2.dist-info/LICENSE.txt
aiida_cp2k_ng-1.0.0b2.dist-info/METADATA
aiida_cp2k_ng-1.0.0b2.dist-info/WHEEL
aiida_cp2k_ng-1.0.0b2.dist-info/entry_points.txt
aiida_cp2k_ng-1.0.0b2.dist-info/top_level.txt
aiida_cp2k_ng-1.0.0b2.dist-info/RECORD
