Metadata-Version: 2.1
Name: aiida-cp2k-ng
Version: 1.0.0b2
Summary: The CP2K plugin for the AiiDA workflow and provenance engine.
Home-page: https://github.com/aiidateam/aiida-cp2k
Author: Ole Schütt, Edward Ditler, Aliaksandr Yakutovich, Patrick Seewald, Tiziano Müller, Andreas Glöss, Leonid Kahle
Author-email: ole.schuett@cp2k.org
License: MIT License
Platform: UNKNOWN
Classifier: License :: OSI Approved :: MIT License
Classifier: Programming Language :: Python :: 2.7
Classifier: Programming Language :: Python :: 3.6
Classifier: Programming Language :: Python :: 3.7
Classifier: Development Status :: 4 - Beta
Requires-Dist: aiida-core (==1.0.0b2)
Requires-Dist: ase
Requires-Dist: regex (>=2019.04.14)
Provides-Extra: pre-commit
Requires-Dist: pre-commit (==1.14.4) ; extra == 'pre-commit'
Provides-Extra: testing
Requires-Dist: pgtest (==1.2.0) ; extra == 'testing'
Requires-Dist: pytest (==4.4.1) ; extra == 'testing'
